{
	"SpanOverText": [
		{
			"match": {
				"begin": 2,
				"end": 7
			}
		},
		{
			"match": {
				"begin": 8,
				"end": 13
			}
		},
		{
			"match": {
				"begin": 14,
				"end": 17
			}
		},
		{
			"match": {
				"begin": 18,
				"end": 24
			}
		},
		{
			"match": {
				"begin": 25,
				"end": 29
			}
		},
		{
			"match": {
				"begin": 30,
				"end": 33
			}
		},
		{
			"match": {
				"begin": 34,
				"end": 38
			}
		},
		{
			"match": {
				"begin": 39,
				"end": 42
			}
		}
	],
	"SpanOverUrl": [
		{
			"match": {
				"begin": 0,
				"end": 4,
				"docref": "url"
			}
		},
		{
			"match": {
				"begin": 7,
				"end": 10,
				"docref": "url"
			}
		},
		{
			"match": {
				"begin": 11,
				"end": 18,
				"docref": "url"
			}
		},
		{
			"match": {
				"begin": 19,
				"end": 22,
				"docref": "url"
			}
		}
	]
}